greenify.cpython-310-x86_64-linux-gnu.so
greenify-0.4.4.dist-info/METADATA
greenify-0.4.4.dist-info/WHEEL
greenify-0.4.4.dist-info/top_level.txt
greenify-0.4.4.dist-info/RECORD
greenify-0.4.4.dist-info/licenses/LICENSE
