Metadata-Version: 2.1
Name: greenify
Version: 0.4.4
Summary: Make C module compatible with gevent at runtime.
Home-page: https://github.com/douban/greenify
Author: Zhongbo Tian
Author-email: tianzhongbo@douban.com
License: UNKNOWN
Download-URL: https://github.com/douban/greenify/archive/0.4.4.tar.gz
Platform: Linux
Classifier: Intended Audience :: Developers
Classifier: Operating System :: POSIX :: Linux
Classifier: Programming Language :: C
Classifier: Programming Language :: Cython
Classifier: Programming Language :: Python :: 3
Classifier: Programming Language :: Python :: 3.9
Classifier: Programming Language :: Python :: 3.10
Classifier: Programming Language :: Python :: 3.11
Classifier: Programming Language :: Python :: 3.12
Classifier: Programming Language :: Python :: 3.13
Classifier: Programming Language :: Python :: 3.14
Classifier: Programming Language :: Python :: Implementation :: CPython
Classifier: Development Status :: 5 - Production/Stable
Classifier: Operating System :: POSIX :: Linux
Classifier: Intended Audience :: Developers
Classifier: License :: OSI Approved :: BSD License
Classifier: Topic :: Software Development :: Libraries
License-File: LICENSE
